localization_analyzer/__init__.py
localization_analyzer/__version__.py
localization_analyzer/cli.py
localization_analyzer/core/__init__.py
localization_analyzer/core/analyzer.py
localization_analyzer/core/file_manager.py
localization_analyzer/core/health_calculator.py
localization_analyzer/features/__init__.py
localization_analyzer/features/auto_fixer.py
localization_analyzer/features/diff.py
localization_analyzer/features/dynamic_key_analyzer.py
localization_analyzer/features/l10n_generator.py
localization_analyzer/features/l10n_migrator.py
localization_analyzer/features/language_manager.py
localization_analyzer/features/missing_keys_fixer.py
localization_analyzer/features/stats.py
localization_analyzer/features/sync.py
localization_analyzer/features/translator.py
localization_analyzer/features/validator.py
localization_analyzer/frameworks/__init__.py
localization_analyzer/frameworks/base.py
localization_analyzer/frameworks/swift.py
localization_analyzer/reports/__init__.py
localization_analyzer/reports/console_reporter.py
localization_analyzer/reports/html_reporter.py
localization_analyzer/reports/json_reporter.py
localization_analyzer/utils/__init__.py
localization_analyzer/utils/backup.py
localization_analyzer/utils/colors.py
localization_analyzer/utils/config.py
localization_analyzer/utils/logging.py
localization_analyzer/utils/progress.py
localization_analyzer/utils/server.py
localization_analyzer/utils/validators.py
localization_analyzer-1.17.0.dist-info/licenses/LICENSE
localization_analyzer-1.17.0.dist-info/METADATA
localization_analyzer-1.17.0.dist-info/WHEEL
localization_analyzer-1.17.0.dist-info/entry_points.txt
localization_analyzer-1.17.0.dist-info/top_level.txt
localization_analyzer-1.17.0.dist-info/RECORD
