Metadata-Version: 2.4
Name: localization-analyzer
Version: 1.17.0
Summary: Professional localization analyzer for Swift/iOS projects with auto-translation
Home-page: https://github.com/sezginpak/localization-analyzer
Author: Sezgin Paksoy
Author-email: Sezgin Paksoy <sezginpak@gmail.com>
License: MIT
Project-URL: Homepage, https://github.com/sezginpak/localization-analyzer
Project-URL: Documentation, https://github.com/sezginpak/localization-analyzer#readme
Project-URL: Repository, https://github.com/sezginpak/localization-analyzer
Project-URL: Bug Tracker, https://github.com/sezginpak/localization-analyzer/issues
Project-URL: Changelog, https://github.com/sezginpak/localization-analyzer/blob/main/CHANGELOG.md
Keywords: localization,i18n,internationalization,swift,ios,strings,translation,cli
Classifier: Development Status :: 4 - Beta
Classifier: Environment :: Console
Classifier: Intended Audience :: Developers
Classifier: Topic :: Software Development :: Localization
Classifier: Topic :: Software Development :: Internationalization
Classifier: License :: OSI Approved :: MIT License
Classifier: Operating System :: OS Independent
Classifier: Programming Language :: Python :: 3
Classifier: Programming Language :: Python :: 3.8
Classifier: Programming Language :: Python :: 3.9
Classifier: Programming Language :: Python :: 3.10
Classifier: Programming Language :: Python :: 3.11
Classifier: Programming Language :: Python :: 3.12
Requires-Python: >=3.8
License-File: LICENSE
Requires-Dist: pyyaml>=6.0
Requires-Dist: certifi>=2023.0.0
Provides-Extra: dev
Requires-Dist: pytest>=7.0; extra == "dev"
Requires-Dist: pytest-cov>=4.0; extra == "dev"
Requires-Dist: black>=23.0; extra == "dev"
Requires-Dist: flake8>=6.0; extra == "dev"
Requires-Dist: build>=1.0; extra == "dev"
Requires-Dist: twine>=4.0; extra == "dev"
Provides-Extra: watch
Requires-Dist: watchdog>=3.0; extra == "watch"
Provides-Extra: progress
Requires-Dist: tqdm>=4.65; extra == "progress"
Dynamic: author
Dynamic: home-page
Dynamic: license-file
Dynamic: requires-python
